hciw/__init__.py
hciw/distributions.py
hciw/model_diagrams.py
hciw/nodes.py
hciw/results.py
hciw/ruds.py
hciw/server_schedules.py
hciw/service_disciplines.py
hciw/waitlist.py
HCiw-0.0.22.dist-info/LICENSE
HCiw-0.0.22.dist-info/METADATA
HCiw-0.0.22.dist-info/WHEEL
HCiw-0.0.22.dist-info/top_level.txt
HCiw-0.0.22.dist-info/RECORD
